{
  "_GO": 0,
  "_EOS": 1,
  "_UNK": 2,
  "_PAD": 3,
  "I": 4,
  "a": 5,
  "the": 6,
  "is": 7,
  "you": 8,
  "to": 9,
  "for": 10,
  "it": 11,
  "me": 12,
  "What": 13,
  "have": 14,
  "about": 15,
  "of": 16,
  "this": 17,
  "want": 18,
  "its": 19,
  "Thank": 20,
  "and": 21,
  "buy": 22,
  "in": 23,
  "with": 24,
  "like": 25,
  "please": 26,
  "be": 27,
  "good": 28,
  "my": 29,
  "much": 30,
  "It": 31,
  "will": 32,
  "Can": 33,
  "That": 34,
  "me.": 35,
  "Is": 36,
  "Please": 37,
  "am": 38,
  "phone": 39,
  "that": 40,
  "would": 41,
  "I'm": 42,
  "are": 43,
  "show": 44,
  "How": 45,
  "it.": 46,
  "do": 47,
  "Okay,": 48,
  "any": 49,
  "not": 50,
  "Yes,": 51,
  "so": 52,
  "price?": 53,
  "you.": 54,
  "camera": 55,
  "Good": 56,
  "your": 57,
  "book": 58,
  "No,": 59,
  "tell": 60,
  "but": 61,
  "can": 62,
  "I'd": 63,
  "one": 64,
  "me?": 65,
  "on": 66,
  "Do": 67,
  "from": 68,
  "don't": 69,
  "other": 70,
  "looking": 71,
  "EUR.": 72,
  "should": 73,
  "some": 74,
  "an": 75,
  "does": 76,
  "model": 77,
  "what": 78,
  "phone.": 79,
  "Hello,": 80,
  "more": 81,
  "has": 82,
  "know": 83,
  "cost?": 84,
  "help": 85,
  "Tell": 86,
  "camera.": 87,
  "as": 88,
  "which": 89,
  "colour": 90,
  "price": 91,
  "their": 92,
  "features?": 93,
  "purchase": 94,
  "battery": 95,
  "GB": 96,
  "laptop": 97,
  "at": 98,
  "than": 99,
  "features": 100,
  "It's": 101,
  "laptop.": 102,
  "just": 103,
  "brand.": 104,
  "features.": 105,
  "RAM": 106,
  "there": 107,
  "assistance.": 108,
  "think": 109,
  "only": 110,
  "much.": 111,
  "brand": 112,
  "assist": 113,
  "OK,": 114,
  "it?": 115,
  "too": 116,
  "Hello": 117,
  "it's": 118,
  "very": 119,
  "if": 120,
  "colour.": 121,
  "And": 122,
  "between": 123,
  "something": 124,
  "or": 125,
  "how": 126,
  "phone?": 127,
  "This": 128,
  "display": 129,
  "also": 130,
  "I'll": 131,
  "No.": 132,
  "Will": 133,
  "Could": 134,
  "discount": 135,
  "better": 136,
  "My": 137,
  "smartphone": 138,
  "Which": 139,
  "need": 140,
  "budget": 141,
  "one.": 142,
  "must": 143,
  "was": 144,
  "proceed": 145,
  "The": 146,
  "best": 147,
  "make": 148,
  "available": 149,
  "morning.": 150,
  "sure": 151,
  "expensive.": 152,
  "internal": 153,
  "range": 154,
  "Wow,": 155,
  "storage": 156,
  "So,": 157,
  "get": 158,
  "model?": 159,
  "going": 160,
  "RAM.": 161,
  "these": 162,
  "You": 163,
  "go": 164,
  "see": 165,
  "discount.": 166,
  "have?": 167,
  "this.": 168,
  "here": 169,
  "Does": 170,
  "great.": 171,
  "take": 172,
  "decent": 173,
  "good.": 174,
  "her": 175,
  "cost": 176,
  "give": 177,
  "same": 178,
  "wait": 179,
  "size": 180,
  "able": 181,
  "But": 182,
  "Hello.": 183,
  "least": 184,
  "suggest": 185,
  "processor": 186,
  "discount?": 187,
  "then": 188,
  "all": 189,
  "Samsung": 190,
  "help.": 191,
  "both": 192,
  "Thanks": 193,
  "look": 194,
  "model.": 195,
  "camera?": 196,
  "they": 197,
  "colour?": 198,
  "prefer": 199,
  "You.": 200,
  "spend": 201,
  "Oh,": 202,
  "4": 203,
  "low": 204,
  "black": 205,
  "Hi,": 206,
  "fantastic.": 207,
  "smartphone.": 208,
  "disk": 209,
  "looks": 210,
  "come": 211,
  "brand?": 212,
  "afford": 213,
  "She": 214,
  "really": 215,
  "Book": 216,
  "anything": 217,
  "out": 218,
  "Canon": 219,
  "quality": 220,
  "this?": 221,
  "graphics": 222,
  "reservation": 223,
  "200": 224,
  "Are": 225,
  "mAh": 226,
  "laptops": 227,
  "lot": 228,
  "In": 229,
  "Lenovo": 230,
  "He": 231,
  "large": 232,
  "storage?": 233,
  "If": 234,
  "price.": 235,
  "possible": 236,
  "thank": 237,
  "billing.": 238,
  "laptop?": 239,
  "dual": 240,
  "because": 241,
  "can't": 242,
  "high": 243,
  "costly.": 244,
  "I've": 245,
  "300": 246,
  "RAM?": 247,
  "laptops?": 248,
  "up": 249,
  "seems": 250,
  "range.": 251,
  "little": 252,
  "Okay.": 253,
  "there.": 254,
  "That's": 255,
  "Well,": 256,
  "EUR": 257,
  "budget.": 258,
  "brands": 259,
  "gift": 260,
  "Hi.": 261,
  "No": 262,
  "size?": 263,
  "support.": 264,
  "won't": 265,
  "Any": 266,
  "Show": 267,
  "Thanks.": 268,
  "wanted": 269,
  "love": 270,
  "no": 271,
  "Don't": 272,
  "i5": 273,
  "capacity?": 274,
  "trust": 275,
  "bit": 276,
  "Intel": 277,
  "sim": 278,
  "product": 279,
  "processor.": 280,
  "Not": 281,
  "Nikon": 282,
  "most": 283,
  "kind": 284,
  "believe": 285,
  "that's": 286,
  "smartphone?": 287,
  "buying": 288,
  "money.": 289,
  "different": 290,
  "that.": 291,
  "had": 292,
  "HP": 293,
  "capacity": 294,
  "been": 295,
  "within": 296,
  "product.": 297,
  "pretty": 298,
  "friend": 299,
  "still": 300,
  "work": 301,
  "Asus": 302,
  "resolution": 303,
  "black.": 304,
  "space.": 305,
  "battery.": 306,
  "billing?": 307,
  "only.": 308,
  "quality?": 309,
  "now.": 310,
  "could": 311,
  "quite": 312,
  "pay": 313,
  "having": 314,
  "well.": 315,
  "right.": 316,
  "purchasing": 317,
  "isn't": 318,
  "Evening,": 319,
  "4G": 320,
  "picture?": 321,
  "job.": 322,
  "Great,": 323,
  "morning,": 324,
  "One": 325,
  "sure.": 326,
  "she": 327,
  "idea": 328,
  "graphics?": 329,
  "let": 330,
  "Evening.": 331,
  "expensive": 332,
  "big": 333,
  "he": 334,
  "Also,": 335,
  "Just": 336,
  "Huawei": 337,
  "for.": 338,
  "searching": 339,
  "heard": 340,
  "2000": 341,
  "time": 342,
  "1TB": 343,
  "way": 344,
  "EUR?": 345,
  "Vivo": 346,
  "in?": 347,
  "graphics.": 348,
  "few": 349,
  "android": 350,
  "you?": 351,
  "under": 352,
  "available?": 353,
  "4000": 354,
  "specific": 355,
  "those": 356,
  "There": 357,
  "sell": 358,
  "storage.": 359,
  "course.": 360,
  "less": 361,
  "suffice.": 362,
  "500": 363,
  "describe": 364,
  "Okay": 365,
  "two": 366,
  "250": 367,
  "Sure,": 368,
  "quality.": 369,
  "new": 370,
  "hope": 371,
  "great": 372,
  "3000": 373,
  "Still,": 374,
  "max": 375,
  "Acer": 376,
  "maximum": 377,
  "exact": 378,
  "Morning.": 379,
  "2": 380,
  "latest": 381,
  "HTC": 382,
  "phones": 383,
  "deal": 384,
  "now": 385,
  "released": 386,
  "lightweight": 387,
  "Dell": 388,
  "recommend": 389,
  "Apple": 390,
  "Sony": 391,
  "models": 392,
  "smartphones?": 393,
  "right": 394,
  "afternoon.": 395,
  "backup": 396,
  "last": 397,
  "evening.": 398,
  "interested": 399,
  "focus": 400,
  "Brand.": 401,
  "by": 402,
  "time.": 403,
  "SIM": 404,
  "another": 405,
  "resolution?": 406,
  "such": 407,
  "personal": 408,
  "specifications": 409,
  "launched": 410,
  "white": 411,
  "space?": 412,
  "Internal": 413,
  "liked": 414,
  "name": 415,
  "Why": 416,
  "long": 417,
  "might": 418,
  "year": 419,
  "you,": 420,
  "As": 421,
  "use": 422,
  "characteristics?": 423,
  "continue": 424,
  "product?": 425,
  "Its": 426,
  "8": 427,
  "Yes": 428,
  "HDD": 429,
  "when": 430,
  "phones.": 431,
  "particular": 432,
  "sounds": 433,
  "provide": 434,
  "good?": 435,
  "Isn't": 436,
  "picture": 437,
  "Oh": 438,
  "fine.": 439,
  "weight": 440,
  "tablet": 441,
  "saw": 442,
  "range?": 443,
  "inch": 444,
  "specifications?": 445,
  "keep": 446,
  "do.": 447,
  "choice.": 448,
  "What's": 449,
  "name.": 450,
  "one?": 451,
  "space": 452,
  "Sure.": 453,
  "her.": 454,
  "tab": 455,
  "weight?": 456,
  "capacity.": 457,
  "Wow.": 458,
  "weigh?": 459,
  "card": 460,
  "secondary": 461,
  "unique": 462,
  "display.": 463,
  "that?": 464,
  "amount": 465,
  "And,": 466,
  "Around": 467,
  "less.": 468,
  "32": 469,
  "next": 470,
  "above": 471,
  "400": 472,
  "then,": 473,
  "first": 474,
  "ahead.": 475,
  "fine": 476,
  "loves": 477,
  "them": 478,
  "problem.": 479,
  "5000": 480,
  "size.": 481,
  "6000": 482,
  "got": 483,
  "details": 484,
  "gold": 485,
  "everything": 486,
  "suitable": 487,
  "ask": 488,
  "after": 489,
  "may": 490,
  "set": 491,
  "phone,": 492,
  "colours": 493,
  "best.": 494,
  "true.": 495,
  "daughter": 496,
  "Nvidia": 497,
  "not.": 498,
  "specification?": 499,
  "Black": 500,
  "laptop,": 501,
  "64": 502,
  "Oppo": 503,
  "However,": 504,
  "excellent": 505,
  "mobile": 506,
  "A": 507,
  "until": 508,
  "click": 509,
  "Samsung.": 510,
  "helping": 511,
  "nice": 512,
  "about?": 513,
  "selecting": 514,
  "say": 515,
  "similar": 516,
  "myself.": 517,
  "i7": 518,
  "sister.": 519,
  "When": 520,
  "didn't": 521,
  "willing": 522,
  "battery?": 523,
  "Here": 524,
  "sister": 525,
  "mind": 526,
  "talking": 527,
  "Ok,": 528,
  "Billing.": 529,
  "lower": 530,
  "pictures": 531,
  "till": 532,
  "birthday.": 533,
  "main": 534,
  "Core": 535,
  "lot.": 536,
  "RAM,": 537,
  "Coolpix": 538,
  "hold": 539,
  "hoping": 540,
  "Casio": 541,
  "Exilim": 542,
  "Agfa": 543,
  "mobile.": 544,
  "rather": 545,
  "also.": 546,
  "booking": 547,
  "Have": 548,
  "Max": 549,
  "ratings.": 550,
  "booking.": 551,
  "Sounds": 552,
  "guess": 553,
  "Actually,": 554,
  "brother": 555,
  "resolution.": 556,
  "For": 557,
  "then.": 558,
  "priority.": 559,
  "all.": 560,
  "Great!!": 561,
  "always": 562,
  "around": 563,
  "used": 564,
  "Great.": 565,
  "needs": 566,
  "so.": 567,
  "Yes.": 568,
  "nice.": 569,
  "strong": 570,
  "doesn't": 571,
  "All": 572,
  "laptops.": 573,
  "ram": 574,
  "price,": 575,
  "drop.": 576,
  "specification.": 577,
  "pack": 578,
  "than.": 579,
  "buy,": 580,
  "offer?": 581,
  "ePhoto": 582,
  "pricey.": 583,
  "incredible.": 584,
  "Morning,": 585,
  "150": 586,
  "Ram": 587,
  "awesome.": 588,
  "prices?": 589,
  "terms": 590,
  "Windows": 591,
  "But,": 592,
  "many": 593,
  "series": 594,
  "among": 595,
  "available.": 596,
  "use.": 597,
  "told": 598,
  "gaming": 599,
  "well?": 600,
  "5": 601,
  "money": 602,
  "10": 603,
  "choose": 604,
  "screen": 605,
  "find": 606,
  "card?": 607,
  "IdeaPad": 608,
  "memory?": 609,
  "recent": 610,
  "PowerShot": 611,
  "After": 612,
  "birthday": 613,
  "15": 614,
  "ample": 615,
  "costly": 616,
  "there,": 617,
  "cost.": 618,
  "good,": 619,
  "doubt": 620,
  "low-cost": 621,
  "aside": 622,
  "Go": 623,
  "me,": 624,
  "minimum": 625,
  "than,": 626,
  "better.": 627,
  "Should": 628,
  "fantastic": 629,
  "reserve": 630,
  "costs.": 631,
  "off": 632,
  "Dual": 633,
  "who": 634,
  "has?": 635,
  "one,": 636,
  "reference": 637,
  "costs": 638,
  "yes,": 639,
  "start": 640,
  "smartphones": 641,
  "gaming.": 642,
  "explore": 643,
  "them.": 644,
  "Let": 645,
  "exactly": 646,
  "details.": 647,
  "mean": 648,
  "assistance": 649,
  "certain": 650,
  "old": 651,
  "Actually": 652,
  "released?": 653,
  "why": 654,
  "ahead": 655,
  "processor?": 656,
  "wants": 657,
  "use?": 658,
  "selfie": 659,
  "equipped": 660,
  "more.": 661,
  "okay.": 662,
  "Yeah,": 663,
  "blue": 664,
  "difference": 665,
  "it,": 666,
  "care": 667,
  "learn": 668,
  "costs?": 669,
  "using": 670,
  "Graphics": 671,
  "like.": 672,
  "specifications.": 673,
  "purchase.": 674,
  "well": 675,
  "choice": 676,
  "release": 677,
  "thanks": 678,
  "high.": 679,
  "tablet?": 680,
  "great,": 681,
  "Motorola": 682,
  "thanks,": 683,
  "tablet.": 684,
  "disc": 685,
  "Panasonic": 686,
  "over": 687,
  "spare?": 688,
  "May": 689,
  "Xiaomi": 690,
  "Only": 691,
  "EX:": 692,
  "CL30": 693,
  "nvidia": 694,
  "kindly": 695,
  "Morning": 696,
  "hard": 697,
  "invoice.": 698,
  "reputable": 699,
  "cpu.": 700,
  "no.": 701,
  "About": 702,
  "previous": 703,
  "offer": 704,
  "Gionee": 705,
  "impressive.": 706,
  "system.": 707,
  "sizes?": 708,
  "screen.": 709,
  "choosing": 710,
  "out?": 711,
  "office": 712,
  "Since": 713,
  "image": 714,
  "beautiful": 715,
  "look.": 716,
  "Hey,": 717,
  "products": 718,
  "mind.": 719,
  "So": 720,
  "either": 721,
  "brands.": 722,
  "backup?": 723,
  "enough.": 724,
  "put": 725,
  "HP.": 726,
  "requirements.": 727,
  "important": 728,
  "select": 729,
  "MateBook": 730,
  "afternoon,": 731,
  "Anything": 732,
  "getting": 733,
  "camera,": 734,
  "query.": 735,
  "Here,": 736,
  "Give": 737,
  "never": 738,
  "Money": 739,
  "series.": 740,
  "his": 741,
  "else.": 742,
  "daily": 743,
  "photos?": 744,
  "online": 745,
  "father": 746,
  "point": 747,
  "inches.": 748,
  "son": 749,
  "3": 750,
  "GB.": 751,
  "colour,": 752,
  "is?": 753,
  "has.": 754,
  "check": 755,
  "video": 756,
  "best?": 757,
  "whatever": 758,
  "did": 759,
  "season": 760,
  "bad.": 761,
  "minute?": 762,
  "6": 763,
  "while": 764,
  "Mi": 765,
  "specification,": 766,
  "moments": 767,
  "result,": 768,
  "Afternoon,": 769,
  "needed.": 770,
  "Nonetheless,": 771,
  "suppose": 772,
  "enjoys": 773,
  "invest": 774,
  "provide?": 775,
  "characteristics": 776,
  "afraid": 777,
  "prohibitively": 778,
  "excellent.": 779,
  "for?": 780,
  "per": 781,
  "-": 782,
  "confused": 783,
  "operating": 784,
  "forgot": 785,
  "highest": 786,
  "5000mAh": 787,
  "out.": 788,
  "please.": 789,
  "At": 790,
  "They": 791,
  "Would": 792,
  "favourite": 793,
  "so?": 794,
  "rating": 795,
  "worth": 796,
  "models.": 797,
  "know.": 798,
  "have.": 799,
  "proceed.": 800,
  "smartphones.": 801,
  "loved": 802,
  "to.": 803,
  "light": 804,
  "amazing!!": 805,
  "currently": 806,
  "order": 807,
  "lover.": 808,
  "travel": 809,
  "refer": 810,
  "money,": 811,
  "13": 812,
  "normal": 813,
  "feature": 814,
  "even": 815,
  "back?": 816,
  "handset.": 817,
  "familiar": 818,
  "asked": 819,
  "friends": 820,
  "white.": 821,
  "likes": 822,
  "special": 823,
  "reason": 824,
  "link": 825,
  "high?": 826,
  "daughter.": 827,
  "constraints.": 828,
  "intel": 829,
  "zoom": 830,
  "picture.": 831,
  "thanks.": 832,
  "smartphone,": 833,
  "radio": 834,
  "i3": 835,
  "photographer.": 836,
  "1000": 837,
  "another.": 838,
  "Kindly": 839,
  "option?": 840,
  "5.": 841,
  "SSD.": 842,
  "SSD?": 843,
  "SSD": 844,
  "Black.": 845,
  "pixels": 846,
  "Oh.": 847,
  "appreciate": 848,
  "assisting": 849,
  "party": 850,
  "all,": 851,
  "Clik!": 852,
  "reliable": 853,
  "larger": 854,
  "expecting": 855,
  "functionality": 856,
  "handset": 857,
  "capable": 858,
  "trying": 859,
  "euros.": 860,
  "require": 861,
  "GPS": 862,
  "Gionee?": 863,
  "close": 864,
  "Desire": 865,
  "BLU": 866,
  "not?": 867,
  "Maybe": 868,
  "recently": 869,
  "them?": 870,
  "almost": 871,
  "Asus.": 872,
  "somewhere": 873,
  "card.": 874,
  "preference": 875,
  "Wow!!": 876,
  "about.": 877,
  "end": 878,
  "regarding": 879,
  "20": 880,
  "before": 881,
  "else": 882,
  "pay?": 883,
  "slots": 884,
  "Gold": 885,
  "Pro.": 886,
  "posses?": 887,
  "seen": 888,
  "something.": 889,
  "beyond": 890,
  "now?": 891,
  "Sorry,": 892,
  "model,": 893,
  "Xperia": 894,
  "back": 895,
  "display?": 896,
  "Microsoft": 897,
  "1": 898,
  "Suggest": 899,
  "bought": 900,
  "350": 901,
  "okay": 902,
  "i": 903,
  "already": 904,
  "making": 905,
  "Then": 906,
  "issue": 907,
  "financial": 908,
  "makes": 909,
  "options": 910,
  "photo": 911,
  "gave": 912,
  "On": 913,
  "comes": 914,
  "were": 915,
  "Pavilion": 916,
  "details?": 917,
  "made": 918,
  "billing": 919,
  "What!": 920,
  "belongs": 921,
  "Allview": 922,
  "pick": 923,
  "Price": 924,
  "right,": 925,
  "girl": 926,
  "concern.": 927,
  "fabulous": 928,
  "required.": 929,
  "these?": 930,
  "okay,": 931,
  "D": 932,
  "detail.": 933,
  "address": 934,
  "128": 935,
  "Epson": 936,
  "expensive,": 937,
  "brand,": 938,
  "based": 939,
  "features,": 940,
  "life": 941,
  "expected": 942,
  "itself.": 943,
  "think.": 944,
  "higher": 945,
  "software": 946,
  "priority": 947,
  "option.": 948,
  "requirement": 949,
  "decided": 950,
  "black?": 951,
  "Even": 952,
  "iPad": 953,
  "primary": 954,
  "learning": 955,
  "limited": 956,
  "days": 957,
  "with?": 958,
  "type": 959,
  "512": 960,
  "discounted": 961,
  "night.": 962,
  "Amazing.": 963,
  "below": 964,
  "high-quality": 965,
  "Coolpad": 966,
  "quality,": 967,
  "drive.": 968,
  "search": 969,
  "demonstrate": 970,
  "taking": 971,
  "present": 972,
  "target": 973,
  "various": 974,
  "decline.": 975,
  "incredible!!": 976,
  "cool.": 977,
  "terrible.": 978,
  "Well": 979,
  "yes.": 980,
  "feature.": 981,
  "Sim.": 982,
  "ok.": 983,
  "company.": 984,
  "link.": 985,
  "suggested": 986,
  "any?": 987,
  "prices": 988,
  "playing": 989,
  "White": 990,
  "requirement.": 991,
  "final": 992,
  "Battery": 993,
  "gets": 994,
  "deal.": 995,
  "actually": 996,
  "Lenovo.": 997,
  "rating?": 998,
  "information": 999,
  "save": 1000,
  "rating.": 1001,
  "elegant.": 1002,
  "case.": 1003,
  "ratings?": 1004,
  "matters": 1005,
  "budget?": 1006,
  "important.": 1007,
  "graphic": 1008,
  "bigger": 1009,
  "Awesome!!": 1010,
  "look?": 1011,
  "16": 1012,
  "OMG,": 1013,
  "Absolutely,": 1014,
  "image,": 1015,
  "is,": 1016,
  "mAh.": 1017,
  "Android": 1018,
  "spare": 1019,
  "name?": 1020,
  "With": 1021,
  "slots.": 1022,
  "Galaxy": 1023,
  "beautiful.": 1024,
  "bad": 1025,
  "Zenfone": 1026,
  "style": 1027,
  "appealing": 1028,
  "see.": 1029,
  "first.": 1030,
  "feature?": 1031,
  "someone": 1032,
  "thought": 1033,
  "Card?": 1034,
  "Lenovo,": 1035,
  "according": 1036,
  "really.": 1037,
  "photography": 1038,
  "class.": 1039,
  "Make": 1040,
  "digital": 1041,
  "captures": 1042,
  "phones?": 1043,
  "date": 1044,
  "father.": 1045,
  "exercise": 1046,
  "lessons": 1047,
  "drop": 1048,
  "feel": 1049,
  "also,": 1050,
  "work.": 1051,
  "him": 1052,
  "dancing": 1053,
  "fulfils": 1054,
  "14": 1055,
  "silver": 1056,
  "us": 1057,
  "2015": 1058,
  "wife": 1059,
  "2017": 1060,
  "best,": 1061,
  "i3-7020U": 1062,
  "still,": 1063,
  "option": 1064,
  "Alright,": 1065,
  "EUR,": 1066,
  "later.": 1067,
  "photographer,": 1068,
  "perfect": 1069,
  "Samsung,": 1070,
  "suggesting": 1071,
  "later": 1072,
  "same.": 1073,
  "students.": 1074,
  "any.": 1075,
  "tab.": 1076,
  "Of": 1077,
  "thinking": 1078,
  "preferred": 1079,
  "far": 1080,
  "What?": 1081,
  "sale.": 1082,
  "shade": 1083,
  "cousin.": 1084,
  "vivo": 1085,
  "significant": 1086,
  "specs?": 1087,
  "normal.": 1088,
  "NO:": 1089,
  "NO.": 1090,
  "Firstly,": 1091,
  "high-resolution": 1092,
  "Zoom": 1093,
  "memory": 1094,
  "no,": 1095,
  "ASUS": 1096,
  "Yeah": 1097,
  "evening,": 1098,
  "Olympus": 1099,
  "things": 1100,
  "effective": 1101,
  "options.": 1102,
  "pixels.": 1103,
  "handset,": 1104,
  "top": 1105,
  "everyday": 1106,
  "confidence.": 1107,
  "bring": 1108,
  "unable": 1109,
  "time,": 1110,
  "appeals": 1111,
  "own": 1112,
  "question.": 1113,
  "like?": 1114,
  "move": 1115,
  "correct?": 1116,
  "perfect.": 1117,
  "LG": 1118,
  "system?": 1119,
  "color.": 1120,
  "both.": 1121,
  "Note": 1122,
  "exceed": 1123,
  "single": 1124,
  "prefers": 1125,
  "sim.": 1126,
  "Lumia": 1127,
  "latest.": 1128,
  "two.": 1129,
  "OS.": 1130,
  "ratings": 1131,
  "Billing": 1132,
  "Take": 1133,
  "expectations.": 1134,
  "whether": 1135,
  "purposes.": 1136,
  "these.": 1137,
  "trend.": 1138,
  "let's": 1139,
  "specification": 1140,
  "Asus?": 1141,
  "decision.": 1142,
  "fit": 1143,
  "stock?": 1144,
  "profitable": 1145,
  "through": 1146,
  "sale?": 1147,
  "play": 1148,
  "once": 1149,
  "slot.": 1150,
  "forward": 1151,
  "recommend?": 1152,
  "professional": 1153,
  "photographer": 1154,
  "said": 1155,
  "enough": 1156,
  "sure,": 1157,
  "fan": 1158,
  "Vivo.": 1159,
  "son.": 1160,
  "buy.": 1161,
  "launched?": 1162,
  "can't.": 1163,
  "brother.": 1164,
  "lover": 1165,
  "Dell.": 1166,
  "well,": 1167,
  "amazing.": 1168,
  "Radio": 1169,
  "system": 1170,
  "must.": 1171,
  "necessarily": 1172,
  "Perfect.": 1173,
  "Surface": 1174,
  "100": 1175,
  "Hii.": 1176,
  "aware": 1177,
  "black,": 1178,
  "Plus.": 1179,
  "Volte": 1180,
  "XPS": 1181,
  "launch?": 1182,
  "amazing": 1183,
  "awesome!!": 1184,
  "OMG!!": 1185,
  "stock": 1186,
  "thing.": 1187,
  "Before": 1188,
  "Last": 1189,
  "possible.": 1190,
  "central": 1191,
  "There's": 1192,
  "fell": 1193,
  "problem,": 1194,
  "saved": 1195,
  "Please,": 1196,
  "Fair,": 1197,
  "Everything": 1198,
  "fits": 1199,
  "Canon.": 1200,
  "whose": 1201,
  "is.": 1202,
  "Graphics.": 1203,
  "lost": 1204,
  "OMG.": 1205,
  "bank": 1206,
  "years": 1207,
  "total": 1208,
  "along": 1209,
  "artist.": 1210,
  "performance?": 1211,
  "idol": 1212,
  "4s": 1213,
  "billings.": 1214,
  "to?": 1215,
  "Graphics_Card?": 1216,
  "plan": 1217,
  "use.?": 1218,
  "liquid": 1219,
  "X2": 1220,
  "prominent": 1221,
  "trusts": 1222,
  "mine.": 1223,
  "significantly": 1224,
  "pocket.": 1225,
  "wide": 1226,
  "Thanks,": 1227,
  "i5-8250U": 1228,
  "extra": 1229,
  "photoshoot?": 1230,
  "Nice.": 1231,
  "700-900": 1232,
  "Huawei.": 1233,
  "wait.": 1234,
  "HDD.": 1235,
  "her,": 1236,
  "BlackBerry": 1237,
  "our": 1238,
  "also?": 1239,
  "Fujifilm": 1240,
  "year.": 1241,
  "battery,": 1242,
  "sim?": 1243,
  "2007.": 1244,
  "easy": 1245,
  "reasonable": 1246,
  "Ohh,": 1247,
  "in-between": 1248,
  "this:": 1249,
  "some.": 1250,
  "15-": 1251,
  "shallow": 1252,
  "Disk": 1253,
  "3.7": 1254,
  "/": 1255,
  "Samsung?": 1256,
  "business.": 1257,
  "that,": 1258,
  "want.": 1259,
  "mind,": 1260,
  "330S": 1261,
  "disappointing!!": 1262,
  "understand,": 1263,
  "fast.": 1264,
  "be.": 1265,
  "understand": 1266,
  "usual": 1267,
  "pretty.": 1268,
  "Amazing!": 1269,
  "help?": 1270,
  "phenomenal": 1271,
  "everything.": 1272,
  "sale": 1273,
  "teach": 1274,
  "seem": 1275,
  "deciding": 1276,
  "edit": 1277,
  "information.": 1278,
  "buying.": 1279,
  "great!!": 1280,
  "4,": 1281,
  "am.": 1282,
  "Moto": 1283,
  "Z": 1284,
  "satisfied": 1285,
  "mode": 1286,
  "power": 1287,
  "megapixels.": 1288,
  "Blackberry?": 1289,
  "Omg.": 1290,
  "fashion": 1291,
  "range,": 1292,
  "need.": 1293,
  "researched": 1294,
  "looks.": 1295,
  "cousin": 1296,
  "cameras.": 1297,
  "doubt.": 1298,
  "essential": 1299,
  "return": 1300,
  "up.": 1301,
  "else?": 1302,
  "valid": 1303,
  "compared": 1304,
  "Someone": 1305,
  "started": 1306,
  "school.": 1307,
  "500-600": 1308,
  "thing,": 1309,
  "heavy": 1310,
  "photo?": 1311,
  "gives": 1312,
  "carry": 1313,
  "said,": 1314,
  "specs": 1315,
  "powerful": 1316,
  "backup.": 1317,
  "store": 1318,
  "iPhone.": 1319,
  "dimensions": 1320,
  "Yaa.": 1321,
  "fond": 1322,
  "day.": 1323,
  "affordable": 1324,
  "Normal": 1325,
  "explain": 1326,
  "Yaa,": 1327,
  "trusted": 1328,
  "backup,": 1329,
  "current": 1330,
  "user": 1331,
  "tablet,": 1332,
  "underwater.": 1333,
  "https://tse3.mm.bing.net/th?id=OIP.TKuExW5CRNsV6fpYLZBtTAHaIY&pid=Api&P=0&w=300&h=300": 1334,
  "picture:": 1335,
  "try": 1336,
  "couple": 1337,
  "minutes": 1338,
  "Both": 1339,
  "colours?": 1340,
  "C-2000": 1341,
  "item.": 1342,
  "Lumix": 1343,
  "MacBook": 1344,
  "Air?": 1345,
  "wish": 1346,
  "inches,": 1347,
  "younger": 1348,
  "preferable": 1349,
  "ideal": 1350,
  "smaller": 1351,
  "1000.": 1352,
  "sharing": 1353,
  "EOS": 1354,
  "series?": 1355,
  "models?": 1356,
  "mean.": 1357,
  "rest": 1358,
  "Allow": 1359,
  "are.": 1360,
  "fan,": 1361,
  "fantastic!!": 1362,
  "here's": 1363,
  "cards": 1364,
  "life?": 1365,
  "sufficient": 1366,
  "photos": 1367,
  "images.": 1368,
  "mine,": 1369,
  "outstanding": 1370,
  "variety": 1371,
  "birthday,": 1372,
  "exclusive": 1373,
  "offers?": 1374,
  "cameras": 1375,
  "fine,": 1376,
  "process.": 1377,
  "advance": 1378,
  "Her": 1379,
  "Excellent!!": 1380,
  "satisfactory?": 1381,
  "previously": 1382,
  "characteristics.": 1383,
  "Without": 1384,
  "mobile,": 1385,
  "while.": 1386,
  "you're": 1387,
  "suffice": 1388,
  "incredible!": 1389,
  "assistance?": 1390,
  "Eluga": 1391,
  "500EUR.": 1392,
  "are,": 1393,
  "Even,": 1394,
  "color": 1395,
  "games.": 1396,
  "positive": 1397,
  "recommendation": 1398,
  "elaborate": 1399,
  "cell.": 1400,
  "portable": 1401,
  "excessive.": 1402,
  "appear?": 1403,
  "functions.": 1404,
  "photograph?": 1405,
  "LG,": 1406,
  "wanted.": 1407,
  "prior": 1408,
  "less,": 1409,
  "performance.": 1410,
  "windows": 1411,
  "Nowadays": 1412,
  "950": 1413,
  "Meizu.": 1414,
  "Pro": 1415,
  "6s": 1416,
  "By": 1417,
  "M3": 1418,
  "Graphic": 1419,
  "design": 1420,
  "256": 1421,
  "desire": 1422,
  "HTC.": 1423,
  "latest?": 1424,
  "816": 1425,
  "performance": 1426,
  "Samsung's": 1427,
  "AMOLED.": 1428,
  "tablets": 1429,
  "Kindle": 1430,
  "Fire": 1431,
  "HDX": 1432,
  "8.9.": 1433,
  "favourite.": 1434,
  "decide": 1435,
  "Perfect!!": 1436,
  "discounts": 1437,
  "cash": 1438,
  "payment?": 1439,
  "choose?": 1440,
  "know,": 1441,
  "use,": 1442,
  "2500": 1443,
  "First,": 1444,
  "prove": 1445,
  "Nice!!": 1446,
  "address.": 1447,
  "games": 1448,
  "longer": 1449,
  "curious": 1450,
  "samsung.": 1451,
  "requirements": 1452,
  "future.": 1453,
  "GB?": 1454,
  "mentioned.": 1455,
  "weighs?": 1456,
  "found": 1457,
  "dream": 1458,
  "Radio?": 1459,
  "You!!": 1460,
  "rated": 1461,
  "way.": 1462,
  "Apple.": 1463,
  "pixel": 1464,
  "ever": 1465,
  "Sony's": 1466,
  "pixel?": 1467,
  "fulfilling": 1468,
  "old.": 1469,
  "fact": 1470,
  "pixels?": 1471,
  "detail": 1472,
  "nothing.": 1473,
  "None": 1474,
  "expect": 1475,
  "handy": 1476,
  "inch.": 1477,
  "Sure": 1478,
  "bet": 1479,
  "MSI": 1480,
  "You!": 1481,
  "lightweight?": 1482,
  "ads": 1483,
  "2000-3000": 1484,
  "Lenovo?": 1485,
  "good!!": 1486,
  "sent": 1487,
  "photography.": 1488,
  "Then,": 1489,
  "wedding": 1490,
  "profession,": 1491,
  "UHD": 1492,
  "idea.": 1493,
  "soon.": 1494,
  "game": 1495,
  "friend?": 1496,
  "inch?": 1497,
  "recommended": 1498,
  "1500": 1499,
  "can.": 1500,
  "review": 1501,
  "being": 1502,
  "present,": 1503,
  "showed": 1504,
  "screen?": 1505,
  "Something": 1506,
  "looks,": 1507,
  "reference.": 1508,
  "think,": 1509,
  "connection": 1510,
  "Google": 1511,
  "problem!!": 1512,
  "Mobile": 1513,
  "here.": 1514,
  "particularly": 1515,
  "priced": 1516,
  "Z5": 1517,
  "Premium": 1518,
  "Dual.": 1519,
  "far.": 1520,
  "looks?": 1521,
  "Good.": 1522,
  "Yup,": 1523,
  "slight": 1524,
  "https://fdn2.gsmarena.com/vv/bigpic/motorola-backflip-motus.jpg": 1525,
  "Lte?": 1526,
  "carry?": 1527,
  "Ok.": 1528,
  "products.": 1529,
  "sure?": 1530,
  "line.": 1531,
  "though?": 1532,
  "came": 1533,
  "suffice?": 1534,
  "case,": 1535,
  "capabilities": 1536,
  "days.": 1537,
  "hurry": 1538,
  "end.": 1539,
  "with.": 1540,
  "photo.": 1541,
  "mid": 1542,
  "Blackberry": 1543,
  "Blackberry.": 1544,
  "husband.": 1545,
  "pick.": 1546,
  "this,": 1547,
  "anyone.": 1548,
  "do?": 1549,
  "check.": 1550,
  "aquamarine": 1551,
  "can,": 1552,
  "mention": 1553,
  "bragging": 1554,
  "recommending?": 1555,
  "Oppo.": 1556,
  "moment.": 1557,
  "limit.": 1558,
  "friend.": 1559,
  "happy": 1560,
  "case": 1561,
  "apart": 1562,
  "Ram?": 1563,
  "hd": 1564,
  "windows.": 1565,
  "pro": 1566,
  "comparison": 1567,
  "gift?": 1568,
  "1200": 1569,
  "education.": 1570,
  "wallet.": 1571,
  "launched.": 1572,
  "slot,": 1573,
  "3400": 1574,
  "least,": 1575,
  "status": 1576,
  "Display": 1577,
  "average": 1578,
  "qualities?": 1579,
  "someone?": 1580,
  "mid-range": 1581,
  "downside.": 1582,
  "Thanks!!": 1583,
  "lover,": 1584,
  "OS": 1585,
  "demand.": 1586,
  "resolution,": 1587,
  "1997.": 1588,
  "please?": 1589,
  "X4": 1590,
  "Soul": 1591,
  "Christmas.": 1592,
  "standard": 1593,
  "apple": 1594,
  "now,": 1595,
  "wife.": 1596,
  "Meteor": 1597,
  "little.": 1598,
  "Gray": 1599,
  "trustworthy": 1600,
  "SSD/1TB": 1601,
  "AMD": 1602,
  "Radeon": 1603,
  "530": 1604,
  "(4": 1605,
  "GB)": 1606,
  "inches": 1607,
  "1152": 1608,
  "39": 1609,
  "zooms": 1610,
  "1999.": 1611,
  "We": 1612,
  "sapphire": 1613,
  "much,": 1614,
  "bing.": 1615,
  "before.": 1616,
  "g": 1617,
  "home.": 1618,
  "(PCIe": 1619,
  "SSD)": 1620,
  "YU": 1621,
  "before?": 1622,
  "year?": 1623,
  "LAVA": 1624,
  "Storage": 1625,
  "http//tse1.mm.bing.net/th?id=OIP.0VqXulY5zGDnRY0yzpA2VQHaFZ&pid=Api&P=0&w=218&h=160": 1626,
  "comfortable": 1627,
  "40.": 1628,
  "minimal": 1629,
  "SIM?": 1630,
  "releases": 1631,
  "gift,": 1632,
  "7800": 1633,
  "NVIDIA": 1634,
  "https://tse1.mm.bing.net/th?id=OIP.Xjgc608ACk8LU0XHcH0ICwHaHa&pid=Api&P=0&w=300&h=300": 1635,
  "radio?": 1636,
  "Previously": 1637,
  "ready": 1638,
  "Xplay5": 1639,
  "knowledge": 1640,
  "specific,": 1641,
  "irrespective": 1642,
  "artist,": 1643,
  "200-": 1644,
  "nothing": 1645,
  "sort.": 1646,
  "Gold?": 1647,
  "actually,": 1648,
  "V5s,": 1649,
  "Seal": 1650,
  "Sister.": 1651,
  "expensive!": 1652,
  "Never": 1653,
  "asking": 1654,
  "Now": 1655,
  "reach": 1656,
  "nice!!": 1657,
  "L1?": 1658,
  "200-300": 1659,
  "excellent,": 1660,
  "Agreed,": 1661,
  "Okay,I": 1662,
  "alternative.": 1663,
  "designer.": 1664,
  "Features": 1665,
  "friends.": 1666,
  "Prior": 1667,
  "artist": 1668,
  "tool.": 1669,
  "go.": 1670,
  "elder": 1671,
  "S7": 1672,
  "expected.": 1673,
  "be,": 1674,
  "issue.": 1675,
  "except": 1676,
  "https://drop.ndtv.com/TECH/product_database/images/82201685704PM_635_samsung_galaxy_note7.jpeg?downsize=*:180&output-quality=80&output-format=webp": 1677,
  "wonder": 1678,
  "too.": 1679,
  "sorry.": 1680,
  "minute": 1681,
  "beginner.": 1682,
  "Oppo,": 1683,
  "market": 1684,
  "14-": 1685,
  "suggested?": 1686,
  "point.": 1687,
  "guidance.": 1688,
  "reference?": 1689,
  "sincerely": 1690,
  "flexible": 1691,
  "Force.": 1692,
  "700": 1693,
  "payment": 1694,
  "https://media.croma.com/image/upload/f_auto,q_auto,d_Croma%20Assets:no-product-image.jpg,h_350,w_350/v1605110756/Croma%20Assets/Communication/Mobiles/Images/8811666898974.jpg": 1695,
  "query": 1696,
  "add": 1697,
  "guess.": 1698,
  "Lava": 1699,
  "Z25": 1700,
  "3020": 1701,
  "issues.": 1702,
  "Yesterday": 1703,
  "we": 1704,
  "number": 1705,
  "pictures.": 1706,
  "passer-by": 1707,
  "Gold.": 1708,
  "looked": 1709,
  "God.": 1710,
  "confused.": 1711,
  "These": 1712,
  "low.": 1713,
  "S80.": 1714,
  "mom.": 1715,
  "mom": 1716,
  "V5": 1717,
  "solve": 1718,
  "back.": 1719,
  "none.": 1720,
  "Well.": 1721,
  "SIM.": 1722,
  "V5s.": 1723,
  "addict.": 1724,
  "suggest?": 1725,
  "features?.": 1726,
  "Won't": 1727,
  "editing": 1728,
  "days,": 1729,
  "fast": 1730,
  "necessary.": 1731,
  "perspective,": 1732,
  "minutes?": 1733,
  "F3": 1734,
  "coming": 1735,
  "gift.": 1736,
  "Keep": 1737,
  "Help": 1738,
  "Please.": 1739,
  "Awesome.": 1740,
  "Let's": 1741,
  "begin": 1742,
  "Yu": 1743,
  "Yunicorn.": 1744,
  "knows": 1745,
  "everything,": 1746,
  "got.": 1747,
  "Can't": 1748,
  "cheaper.": 1749,
  "beginners.": 1750,
  "realised": 1751,
  "research": 1752,
  "contact": 1753,
  "thing": 1754,
  "thin": 1755,
  "Recommend": 1756,
  "android?": 1757,
  "colours.": 1758,
  "loyal": 1759,
  "grey.": 1760,
  "feeling": 1761,
  "megapixels": 1762,
  "head": 1763,
  "turning": 1764,
  "effect": 1765,
  "everyone.": 1766,
  "effect.": 1767,
  "iPhones.": 1768,
  "premium": 1769,
  "leave": 1770,
  "me.?": 1771,
  "travelling.": 1772,
  "100.": 1773,
  "glad": 1774,
  "becomes": 1775,
  "XZ": 1776,
  "expensive?": 1777,
  "U11?": 1778,
  "16MP": 1779,
  "calls.": 1780,
  "https://drop.ndtv.com/TECH/product_database/images/htc_u_ultra_3960_480X960_329201793557AM.png?downsize=*:180&output-quality=80&output-format=webp": 1781,
  "tabs.": 1782,
  "0.004882": 1783,
  "studies?": 1784,
  "data": 1785,
  "tab?": 1786,
  "iPhones": 1787,
  "sell?": 1788,
  "mini": 1789,
  "course,": 1790,
  "Iconia": 1791,
  "B1:820.": 1792,
  "110": 1793,
  "13MP.": 1794,
  "420": 1795,
  "15.6": 1796,
  "CPU?": 1797,
  "S500.": 1798,
  "S600": 1799,
  "S500?": 1800,
  "Woah!": 1801,
  "S600.": 1802,
  "better?": 1803,
  "0.004882813": 1804,
  "condition": 1805,
  "5G": 1806,
  "planning": 1807,
  "cost-effective": 1808,
  "extensive": 1809,
  "Because": 1810,
  "https://tse2.mm.bing.net/th?id=OIP.jI5-hyDmoBxZp_7ftPZUWgHaHE&pid=Api&P=0&w=160&h=153": 1811,
  "confirm": 1812,
  "Gionee.": 1813,
  "2014.": 1814,
  "prices.": 1815,
  "difference.": 1816,
  "book.": 1817,
  "4500mAh.": 1818,
  "2?": 1819,
  "2.": 1820,
  "No.Thank": 1821,
  "three?": 1822,
  "link:": 1823,
  "Kyocera": 1824,
  "Finecam": 1825,
  "S340.": 1826,
  "7900.": 1827,
  "Leica": 1828,
  "V-LUX": 1829,
  "1.": 1830,
  "another?": 1831,
  "Life": 1832,
  "drops.": 1833,
  "recently.": 1834,
  "format": 1835,
  "pleasant": 1836,
  "i7.": 1837,
  "ideal.": 1838,
  "6483": 1839,
  "famous": 1840,
  "DC4800": 1841,
  "D70": 1842,
  "1000-2000": 1843,
  "monitor": 1844,
  "i3?": 1845,
  "drive?": 1846,
  "Matebook": 1847,
  "i7-8565U": 1848,
  "2000.": 1849,
  "600": 1850,
  "Nokia": 1851,
  "lovely": 1852,
  "type?": 1853,
  "resolutions?": 1854,
  "easier": 1855,
  "way?": 1856,
  "sorry,": 1857,
  "tablets.": 1858,
  "ranges": 1859,
  "dual-sim": 1860,
  "camera's": 1861,
  "gadget.": 1862,
  "yourself": 1863,
  "plenty": 1864,
  "working": 1865,
  "notify": 1866,
  "sensor": 1867,
  "undecided": 1868,
  "capacities?": 1869,
  "work,": 1870,
  "item": 1871,
  "transaction.": 1872,
  "recall": 1873,
  "present?": 1874,
  "specifications,": 1875,
  "older": 1876,
  "learned": 1877,
  "huge": 1878,
  "educational": 1879,
  "cards.": 1880,
  "believes": 1881,
  "sum": 1882,
  "definitely": 1883,
  "negative": 1884,
  "life,": 1885,
  "memory,": 1886,
  "providing": 1887,
  "regular": 1888,
  "basis.": 1889,
  "https://www.": 1890,
  "laptopmain.com/wp-content/uploads/2018/05/Dell-G7-7588-Review-1.jpg": 1891,
  "meets": 1892,
  "criterion": 1893,
  "time?": 1894,
  "opinion,": 1895,
  "faith": 1896,
  "being,": 1897,
  "daughter's": 1898,
  "panel": 1899,
  "watch": 1900,
  "minutes.": 1901,
  "Silver": 1902,
  "options?": 1903,
  "data.": 1904,
  "Brand": 1905,
  "fantastic,": 1906,
  "GPS?": 1907,
  "ambition": 1908,
  "well-known": 1909,
  "focus?": 1910,
  "wondering": 1911,
  "visual": 1912,
  "means.": 1913,
  "requirements?": 1914,
  "so,": 1915,
  "blogger,": 1916,
  "Often,": 1917,
  "there's": 1918,
  "cell": 1919,
  "best-selling": 1920,
  "branch": 1921,
  "talk": 1922,
  "potential.": 1923,
  "afternoon?": 1924,
  "adequate": 1925,
  "200-250": 1926,
  "scheme": 1927,
  "gold?": 1928,
  "indeed.": 1929,
  "before,": 1930,
  "That'll": 1931,
  "reality.": 1932,
  "hoped": 1933,
  "possession?": 1934,
  "goodness.": 1935,
  "upon": 1936,
  "it'd": 1937,
  "While": 1938,
  "agree,": 1939,
  "cheaper": 1940,
  "Approximately": 1941,
  "goodness!!": 1942,
  "there?": 1943,
  "white,": 1944,
  "kid,": 1945,
  "tight": 1946,
  "LG.": 1947,
  "Optimus": 1948,
  "other.": 1949,
  "Mark": 1950,
  "III": 1951,
  "D-3600": 1952,
  "DSLR": 1953,
  "17.3": 1954,
  "4500": 1955,
  "250EUR.": 1956,
  "mp": 1957,
  "Ray": 1958,
  "Clearly": 1959,
  "4GB": 1960,
  "run": 1961,
  "additional": 1962,
  "goodness!": 1963,
  "rates": 1964,
  "batteries?": 1965,
  "lookout": 1966,
  "producing": 1967,
  "extremely": 1968,
  "Really,": 1969,
  "you've": 1970,
  "inside?": 1971,
  "doubt,": 1972,
  "item?": 1973,
  "hunting": 1974,
  "seemed": 1975,
  "god.": 1976,
  "machine.": 1977,
  "decision?": 1978,
  "addition,": 1979,
  "worry": 1980,
  "reservation.": 1981,
  "have,": 1982,
  "That'd": 1983,
  "read": 1984,
  "misplaced": 1985,
  "appealing.": 1986,
  "waste": 1987,
  "listening": 1988,
  "radio.": 1989,
  "me.\"": 1990,
  "question": 1991,
  "head-turning": 1992,
  "it'll": 1993,
  "specs,": 1994,
  "bag.": 1995,
  "though.": 1996,
  "often.": 1997,
  "inform": 1998,
  "sweet.": 1999,
  "convince": 2000,
  "daughter,": 2001,
  "X543MA": 2002,
  "there!": 2003,
  "of?": 2004,
  "7900": 2005,
  "fall,": 2006,
  "suggestion": 2007,
  "i.e.": 2008,
  "suggestion.": 2009,
  "Exactly": 2010,
  "G5": 2011,
  "glad.": 2012,
  "done.": 2013,
  "color?": 2014,
  "https://www.maxbhi.com/images/thumbnails/400/400/detailed/2157/full_body_housing_for_zopo_color_f5_gold_maxbhi.com_95856.jpg": 2015,
  "micromax": 2016,
  "Canvas": 2017,
  "Evok": 2018,
  "it..": 2019,
  "variant.": 2020,
  "task.": 2021,
  "NVMe": 2022,
  "M.2": 2023,
  "SSD/1": 2024,
  "TB": 2025,
  "3000-4000": 2026,
  "euros?": 2027,
  "graphics,": 2028,
  "OK.": 2029,
  "Proceeded": 2030,
  "service.": 2031,
  "Contact": 2032,
  "20mp": 2033,
  "awesome": 2034,
  "confusion": 2035,
  "reading": 2036,
  "interesting": 2037,
  "only?": 2038,
  "wife?": 2039,
  "learner": 2040,
  "120": 2041,
  "180": 2042,
  "learner?": 2043,
  "owns?": 2044,
  "ensure": 2045,
  "game.": 2046,
  "Thats": 2047,
  "golden": 2048,
  "capacity?.": 2049,
  "value?": 2050,
  "tough": 2051,
  "guess,": 2052,
  "bride.": 2053,
  "Pearl": 2054,
  "Sure!!": 2055,
  "those.": 2056,
  "E": 2057,
  "8.0": 2058,
  "weighs.": 2059,
  "dell.": 2060,
  "work?": 2061,
  "college": 2062,
  "student,": 2063,
  "frequently,": 2064,
  "charge": 2065,
  "good!!\nI": 2066,
  "slots?": 2067,
  "near": 2068,
  "preferring": 2069,
  "2272": 2070,
  "1600": 2071,
  "moment?": 2072,
  "Amongst": 2073,
  "ones": 2074,
  "gallery": 2075,
  "-\nhttps://cdn.gadgets360.com/content/assets/products/huawei-mediapad-x2-2440_960X480_1438858207.jpg?downsize=*:180&output-quality=80&output-format=webp": 2076,
  "True,": 2077,
  "snow": 2078,
  "one??": 2079,
  "value": 2080,
  "random": 2081,
  "judge": 2082,
  "belong": 2083,
  "Huawei's": 2084,
  "feels": 2085,
  "approx": 2086,
  "graphics?\nI": 2087,
  "insights": 2088,
  "Great!!\nHow": 2089,
  "problem": 2090,
  "Great!!\nWhat": 2091,
  "Evening!!\nI": 2092,
  "enquire": 2093,
  "stars": 2094,
  "enough?": 2095,
  "HP?": 2096,
  "star": 2097,
  "chance": 2098,
  "pixel.": 2099,
  "reaching": 2100,
  "conclusion.": 2101,
  "Interesting!!": 2102,
  "necessary": 2103,
  "requirement,": 2104,
  "more?": 2105,
  "requests?": 2106,
  "OMG!": 2107,
  "Ricoh": 2108,
  "change": 2109,
  "Fine.": 2110,
  "Thankyou.": 2111,
  "slim": 2112,
  "Link-": 2113,
  "https://www.google.com/url?sa=i&url=https%3A%2F%2Fgadgets.ndtv.com%2Fmobiles%2Fnews%2Fblackberry-porsche-design-p9983-graphite-premium-smartphone-launched-671420&psig=AOvVaw1ldICjmOhO8HAIe35KiI1G&ust=1621074890272000&source=images&cd=vfe&ved=2ahUKEwi8opfZ_MjwAhXKNCsKHUxkAhIQr4kDegUIARC1AQ": 2114,
  "expectation.": 2115,
  "badly.": 2116,
  "value.": 2117,
  "display,": 2118,
  "bad!!": 2119,
  "Nice": 2120,
  "one!!": 2121,
  "slot": 2122,
  "https://www.google.com/url?sa=i&url=https%3A%2F%2Fwww.91mobiles.com%2Fxiaomi-mi-pad-3-price-in-india&psig=AOvVaw1nSrldr4WsiAeapBRtSFrI&ust=1621074963641000&source=images&cd=vfe&ved=2ahUKEwinrZX8_MjwAhVVhUsFHVp9DkcQr4kDegUIARC7AQ": 2123,
  "touring": 2124,
  "places.": 2125,
  "2020.": 2126,
  "rethink": 2127,
  "Anyways,": 2128,
  "17": 2129,
  "cameras?": 2130,
  "Nice,": 2131,
  "shown": 2132,
  "https://www.google.com/url?sa=i&url=https%3A%2F%2Fwww.gadgetsnow.com%2Fmobile-phones%2FVivo-V5s&psig=AOvVaw2OzEfurJuy-BNdPPDjtxs8&ust=1621075010688000&source=images&cd=vfe&ved=2ahUKEwjt8MyS_cjwAhUFiksFHXyeAR0Qr4kDegUIARDVAQ": 2133,
  "handy?": 2134,
  "recently?": 2135,
  "Tv": 2136,
  "times.": 2137,
  "https://drop.ndtv.com/TECH/product_database/images/662017104802AM_635_oppor11_db.jpeg?downsize=*:180&output-quality=80&output-format=webp": 2138,
  "good!": 2139,
  "https://data.ibtimes.sg/en/full/3718/motorola-moto-maxx.jpg": 2140,
  "detailed": 2141,
  "colour.\nhttps://www.maxbhi.com/images/thumbnails/50/50/detailed/1749/full_body_housing_for_lenovo_phab_2_pro_gunmetal_grey_maxbhi_com_4716.jpg": 2142,
  "related": 2143,
  "Great!!\nThis": 2144,
  "foe": 2145,
  "120-150": 2146,
  "most.": 2147,
  "dimension?": 2148,
  "specified": 2149,
  "purpose?": 2150,
  "powershot": 2151,
  "A540,": 2152,
  "revisit": 2153,
  "forget": 2154,
  "girlfriend.": 2155,
  "aspect": 2156,
  "Z3v.": 2157,
  "successful": 2158,
  "photography?": 2159,
  "pictures?": 2160,
  "Has": 2161,
  "worthy": 2162,
  "buy?": 2163,
  "bad!": 2164,
  "USP?": 2165,
  "Aren't": 2166,
  "https://drop.ndtv.com/TECH/product_database/images/5302013121155AM_635_sony_xperia_tipo.png?downsize=*:180&output-quality=80&output-format=webp": 2167,
  "brown.": 2168,
  "kid's": 2169,
  "orange": 2170,
  "https://www.google.com/url?sa=i&url=https%3A%2F%2Fgadgets.ndtv.com%2Fzte-open-c-1302&psig=AOvVaw3Y0GzOtyZqNUKPSungY8vv&ust=1621075421292000&source=images&cd=vfe&ved=2ahUKEwjJirLW_sjwAhXaw3MBHcZSBdsQr4kDegUIARCwAQ": 2171,
  "works": 2172,
  "law.": 2173,
  "samsung": 2174,
  "one-\nhttps://www.google.com/url?sa=i&url=https%3A%2F%2Fwww.gadgetsnow.com%2Fmobile-phones%2FSamsung-Galaxy-Neo-SHW-M220L&psig=AOvVaw2lOGzDofDG9Iaf9bClB2Gm&ust=1621075708399000&source=images&cd=vfe&ved=2ahUKEwi026Xf_8jwAhVFKHIKHZ1iAa8Qr4kDegUIARCvAQ": 2175,
  "Hwm": 2176,
  "sister?": 2177,
  "how's": 2178,
  "customers?": 2179,
  "Amazing!!": 2180,
  "Perfect": 2181,
  "helpful.": 2182,
  "320-15IKBRA?": 2183,
  "exceeds": 2184,
  "uttermost": 2185,
  "importance.": 2186,
  "this\nhttps://images-na.ssl-images-amazon.com/images/I/91DBPouuFkL._AC_SL1500_.jpg": 2187,
  "gray.": 2188,
  "Really": 2189,
  "gorgeous.": 2190,
  "13.": 2191,
  "preference.": 2192,
  "yourself.": 2193,
  "X7": 2194,
  "Good!!": 2195,
  "Lte": 2196,
  "oriented": 2197,
  "compromise": 2198,
  "https://www.google.com/url?sa=i&url=https%3A%2F%2Fwww.pinterest.com%2Fpin%2F78742693460497866%2F&psig=AOvVaw2qY7_v95rYdMKTmpRaCkM7&ust=1621076000607000&source=images&cd=vfe&ved=2ahUKEwj41NDqgMnwAhWYkUsFHfZcBUgQr4kDegUIARClAQ": 2199,
  "eyes": 2200,
  "9380": 2201,
  "Nexus": 2202,
  "(2013": 2203,
  "Edition)": 2204,
  "Look,": 2205,
  "Omg": 2206,
  "surprised": 2207,
  "offers.": 2208,
  "T-": 2209,
  "G2x": 2210,
  "https://fdn2.gsmarena.com/vv/bigpic/t-mobile-g2x.jpg": 2211,
  "Right,": 2212,
  "inquired": 2213,
  "urgency.": 2214,
  "help!!": 2215,
  "definitely.": 2216,
  "Cool!!": 2217,
  "loving": 2218,
  "brother?": 2219,
  "17-18": 2220,
  "party.": 2221,
  "Ericsson.": 2222,
  "shade.": 2223,
  "reasons,": 2224,
  "somehow": 2225,
  "expectations": 2226,
  "here?": 2227,
  "15-da0007nx.": 2228,
  "payment,": 2229,
  "sells": 2230,
  "https://fdn2.gsmarena.com/vv/bigpic/asus-zenfone-live-zb501kl.jpg": 2231,
  "multitask.": 2232,
  "Android?": 2233,
  "Perhaps": 2234,
  "wearing": 2235,
  "constraint.": 2236,
  "Now,": 2237,
  "unquestionably": 2238,
  "superior": 2239,
  "inventory?": 2240,
  "at.": 2241,
  "booked.": 2242,
  "Image": 2243,
  "https://drop.ndtv.com/TECH/product_database/images/6132017104218AM_635_motoe4db.jpeg?downsize=*:180&output-quality=80&output-format=webp\nWhat": 2244,
  "feasible": 2245,
  "doing": 2246,
  "highly": 2247,
  "absolutely": 2248,
  "rated?": 2249,
  "tab,": 2250,
  "metro": 2251,
  "https://encrypted-tbn0.gstatic.com/images?q=tbn:ANd9GcSompvLwfDaxU1vboEYMLNQKdLBfeI3pcmBSvakDaooN6IPf2E4S5icFgheE1Tu-1LjXo3qyiI&usqp=CAc": 2252,
  "2000-3000.": 2253,
  "bilings?": 2254,
  "into": 2255,
  "Here,\nhttps://encrypted-tbn0.gstatic.com/images?q=tbn:ANd9GcSWe5tBueyevcQFSaAiHg2l_zvccKd7Rd55KQ&usqp=CAU": 2256,
  "usually": 2257,
  "320-15IKBRN.": 2258,
  "Somewhere": 2259,
  "1500-2000": 2260,
  "professor": 2261,
  "A300.": 2262,
  "limitation.": 2263,
  "Other": 2264,
  "aspects?": 2265,
  "fo": 2266,
  "frenemy": 2267,
  "https://www.google.com/imgres?imgurl=https%3A%2F%2F360view.hum3d.com%2Fzoom%2FAcer%2FAcer_Liquid_Z500_Green_1000_0002.jpg&imgrefurl=https%3A%2F%2Fhum3d.com%2F3d-models%2Facer-liquid-z500-aquamarine-green%2F&tbnid=x0fZNHOxj2bjpM&vet=12ahUKEwicgujvhMnwAhUjNXIKHV4zBFcQMygCegQIARB6..i&docid=SraD7s9uyMLP9M&w=1000&h=1000&itg=1&q=Acer%20Liquid%20Z500%20smartphone%20in%20aquamarine%20grey&hl=en&ved=2ahUKEwicgujvhMnwAhUjNXIKHV4zBFcQMygCegQIARB6": 2268,
  "Liquid": 2269,
  "Z500": 2270,
  "Acer.": 2271,
  "grey": 2272,
  "yeah,": 2273,
  "asked?": 2274,
  "basis": 2275,
  "state": 2276,
  "Colour.": 2277,
  "Right.": 2278,
  "possess?": 2279,
  "GPU?": 2280,
  "14-bf102nx,": 2281,
  "suit": 2282,
  "joined": 2283,
  "week": 2284,
  "genius.": 2285,
  "considered": 2286,
  "piggy": 2287,
  "Iaptops": 2288,
  "TV.": 2289,
  "Absolutely": 2290,
  "satisfying.": 2291,
  "Some": 2292,
  "S145": 2293,
  "determined": 2294,
  "couldn't.": 2295,
  "Awesome!!\nBook": 2296,
  "so?\nI": 2297,
  "view": 2298,
  "why?": 2299,
  "prime": 2300,
  "Amazing,": 2301,
  "X3": 2302,
  "souln": 2303,
  "ipad": 2304,
  "12.9?": 2305,
  "price?Which": 2306,
  "remember": 2307,
  "https://encrypted-tbn0.gstatic.com/images?q=tbn:ANd9GcSQd2qDeWSHNYL5otcFdW7VgjMG0eGWeiIVJ1JMxs2uCvjnyelq_iceHueztM5AZrbVgFI&usqp=CAU": 2308,
  "person.": 2309,
  "given": 2310,
  "Yes,,": 2311,
  "All,": 2312,
  "quiet": 2313,
  "down": 2314,
  "side.": 2315,
  "part.": 2316,
  "seek": 2317,
  "suggestions": 2318,
  "internal_": 2319,
  "Satisfying": 2320,
  "though!!": 2321,
  "Z6": 2322,
  "plus": 2323,
  "Zest?": 2324,
  "comparisons": 2325,
  "lower?": 2326,
  "Looking": 2327,
  "https://www.gsmarena.com/acer_liquid_z6_plus-pictures-8305.php": 2328,
  "keen": 2329,
  "support?": 2330,
  "finalize": 2331,
  "2000EUR.": 2332,
  "billings?": 2333,
  "considerable": 2334,
  "launch.": 2335,
  "Acer?": 2336,
  "21MP.": 2337,
  "220": 2338,
  "38": 2339,
  "1024": 2340,
  "114": 2341,
  "tele,": 2342,
  "free": 2343,
  "service": 2344,
  "damage": 2345,
  "phone?\"": 2346,
  "game,": 2347,
  "product,": 2348,
  "IN": 2349,
  "options,": 2350,
  "hang": 2351,
  "hangs": 2352,
  "lot?": 2353,
  "IS": 2354,
  "Effective": 2355,
  "old,": 2356,
  "photography,": 2357,
  "perform": 2358,
  "activities": 2359,
  "some?": 2360,
  "OS?": 2361,
  "https://www.laptopmain.com/wp-content/uploads/2018/05/Dell-G7-7588-Review-1.jpg": 2362,
  "300-700": 2363,
  "518": 2364,
  "Huawei?": 2365,
  "aluminium": 2366,
  "least.": 2367,
  "20MP.": 2368,
  "Gray.": 2369,
  "460": 2370,
  "ASJNDCKSJN": 2371,
  "HTC?": 2372,
  "i5-8250U.": 2373,
  "ALNDKA": 2374,
  "nephew": 2375,
  "12546": 2376,
  "BlackBerry?": 2377,
  "blackberry?": 2378,
  "is..........": 2379,
  "comprehensive,": 2380,
  "teacher.": 2381,
  "Hey": 2382,
  "cousin's": 2383,
  "house.": 2384,
  "immediately": 2385,
  "captured": 2386,
  "this:https://tse2.": 2387,
  "Explicit.": 2388,
  "net/th?id=OIP.pFq3U_YiqyCdsRck5uwDYAHaJe&pid=Api&P=0&w=300&h=300": 2389,
  "Deluxe": 2390,
  "ZE551ML": 2391,
  "again": 2392,
  "Fine": 2393,
  "initiate": 2394,
  "assisting.": 2395,
  "Dell?": 2396,
  "1st": 2397,
  "Ram.": 2398,
  "1400": 2399,
  "macro": 2400,
  "low-weight": 2401,
  "Cool,": 2402,
  "abysmal.": 2403,
  "GB,": 2404,
  "Evening": 2405,
  "brand-specific,": 2406,
  "carry.": 2407,
  "70": 2408,
  "A70,": 2409,
  "2003": 2410,
  "dull": 2411,
  "Inspiron": 2412,
  "3567": 2413,
  "https://tse4.mm.bing.net/th?id=OIP.OEDsPwsWhIbc6rNBmKtHBgHaJo&pid=Api&P=0&w=300&h=300": 2414,
  "Storage.": 2415,
  "handle?": 2416,
  "4-star": 2417,
  "trustworthy?": 2418,
  "V20": 2419,
  "become": 2420,
  "4000mAh": 2421,
  "space,": 2422,
  "https://www.gizmochina.com/wp-content/uploads/2017/05/Asus-Zenfone-3-Deluxe-5.5-ZS550KL-120x120.jpg": 2423,
  "15.4": 2424,
  "over-price": 2425,
  "prevalent.": 2426,
  "https://tse4.mm.bing.net/th?id=OIP.piee_apZf4tJx4cPM0qCsQHaHS&pid=Api&P=0&w=166&h=164": 2427,
  "Tomorrow": 2428,
  "10th": 2429,
  "anniversary.": 2430,
  "reels": 2431,
  "video.": 2432,
  "service?": 2433,
  "picture.\nhttp://www.": 2434,
  "techmerry.com/wp-content/uploads/2016/05/Asus-Zenfone-Max.jpg": 2435,
  "selfies": 2436,
  "Low": 2437,
  "Oppo?": 2438,
  "https://tse1.mm.bing.net/th?id=OIP.Nc_GvvfZ3Km35NNpHqJg8gHaFj&pid=Api&P=0&w=205&h=155": 2439,
  "generation": 2440,
  "pink": 2441,
  "https://tse2.mm.bing.net/th?id=OIP.7zEKMpzMbp1f5NuEwwl20AHaFj&pid=Api&P=0&w=210&h=158": 2442,
  "https://tse2.": 2443,
  "explicit.": 2444,
  "net/th?id=OIP.UA85sIrAY-z06kUnc8XAdQAAAA&pid=Api&P=0&w=300&h=300": 2445,
  "15-cs2012nx.": 2446,
  "nephew.": 2447,
  "LeEco": 2448,
  "2016": 2449,
  "JVC": 2450,
  "GC-QX3HD.": 2451,
  "Macro": 2452,
  "somewhere,": 2453,
  "https://cdn.": 2454,
  "ndtv.com/tech/images/gionee_marathon_m5_mini.jpg": 2455,
  "wrong": 2456,
  "impression": 2457,
  "matter.": 2458,
  "invest,": 2459,
  "Elite": 2460,
  "boyfriend": 2461,
  "photoshoot.": 2462,
  "expect.": 2463,
  "Sister": 2464,
  "features?Wow,": 2465,
  "God,": 2466,
  "issue,": 2467,
  "Budget.": 2468,
  "clue.": 2469,
  "Black?": 2470,
  "beautiful,": 2471,
  "manage": 2472,
  "http://cdn2.gsmarena.com/vv/bigpic/huawei-p9-plus.jpg": 2473,
  "similar?": 2474,
  "Fashion": 2475,
  "blogger": 2476,
  "ended": 2477,
  "multi-purpose": 2478,
  "click,": 2479,
  "post": 2480,
  "sellers.": 2481,
  "actually.": 2482,
  "rethink.": 2483,
  "discuss": 2484,
  "finding": 2485,
  "different.": 2486,
  "https://rukminim1.flixcart.com/image/416/416/j45wn0w0/mobile/a/u/t/sony-xperia-xz-premium-dual-g8142-original-imaev4rtmwhmvz8t.jpeg?q=70": 2487,
  "active.": 2488,
  "classmates": 2489,
  "promising.": 2490,
  "Huh?": 2491,
  "God!": 2492,
  "Nevermind,": 2493,
  "generous": 2494,
  "Perfect,": 2495,
  "Certainly,": 2496,
  "understood": 2497,
  "manageable.": 2498,
  "happy!!": 2499,
  "Blue": 2500,
  "expensive..": 2501,
  "sometime": 2502,
  "100-200": 2503,
  "God!!": 2504,
  "expected,": 2505,
  "ofcourse.": 2506,
  "Budget?": 2507,
  "understand.": 2508,
  "present.": 2509,
  "managed": 2510,
  "https://drop.ndtv.com/TECH/product_database/images/46201674055PM_635_huawei_p9_plus.jpeg?downsize=*:180&output-quality=80&output-format=webp": 2511,
  "colours,": 2512,
  "known": 2513,
  "market.": 2514,
  "14-bf102nx": 2515,
  "l.": 2516,
  "rated,": 2517,
  "small.": 2518,
  "remarkable": 2519,
  "P10": 2520,
  "Lite.": 2521,
  "colleagues": 2522,
  "Neither": 2523,
  "nor": 2524,
  "Moto.": 2525,
  "S6": 2526,
  "edge+": 2527,
  "Duos": 2528,
  "relatives.": 2529,
  "antique": 2530,
  "unique.": 2531,
  "remember.": 2532,
  "introducing": 2533,
  "in??": 2534,
  "care.": 2535,
  "Colour,": 2536,
  "Midnight": 2537,
  "onto": 2538,
  "turn": 2539,
  "15.": 2540,
  "megapixel": 2541,
  "Sanyo": 2542,
  "Xacti": 2543,
  "DSC-S4.": 2544,
  "send": 2545,
  "message": 2546,
  "receiver's": 2547,
  "hold?": 2548,
  "Aurora": 2549,
  "Panasonic.": 2550,
  "Nothing.": 2551,
  "Rose": 2552,
  "phenomenal.": 2553,
  "heavy.": 2554,
  "account": 2555,
  "hasn't": 2556,
  "Guess": 2557,
  "designer,": 2558,
  "creates": 2559,
  "Hp": 2560,
  "enough,": 2561,
  "surprise": 2562,
  "recommendation.": 2563,
  "impressive": 2564,
  "coloured": 2565,
  "imagined,": 2566,
  "Ok": 2567,
  "beginner": 2568,
  "u?": 2569,
  "than?": 2570,
  "part": 2571,
  "Gunmetal": 2572,
  "Grey.": 2573,
  "dam": 2574,
  "creating": 2575,
  "switch": 2576,
  "performance-wise?": 2577,
  "plus.": 2578,
  "ver": 2579,
  "stolen": 2580,
  "identify": 2581,
  "again.": 2582,
  "blogger.": 2583,
  "vlogs": 2584,
  "posts": 2585,
  "YouTube.": 2586,
  "11": 2587,
  "simple": 2588,
  "calling": 2589,
  "messaging": 2590,
  "android.": 2591,
  "550": 2592,
  "Crown": 2593,
  "justifiable": 2594,
  "something?": 2595,
  "budding": 2596,
  "will.": 2597,
  "payments": 2598,
  "journalism": 2599,
  "student.": 2600,
  "Also": 2601,
  "assurance.": 2602,
  "doesn't.": 2603,
  "anymore.": 2604,
  "Plus,": 2605,
  "girly": 2606,
  "idea,": 2607,
  "girl's": 2608,
  "deciding.": 2609,
  "updated.": 2610,
  "please,": 2611,
  "arrange": 2612,
  "phone?.": 2613,
  "amodel": 2614,
  "Price?": 2615,
  "electronic": 2616,
  "person": 2617,
  "especially": 2618,
  "demanded": 2619,
  "None.": 2620,
  "memory?.": 2621,
  "helpful?": 2622,
  "https://cdn.hum3d.com/wp-content/uploads/2017/03/10/Huawei_P10_Mystic_Silver_600_lq_0002-118x94.jpg": 2623,
  "lightweight.": 2624,
  "A10.": 2625,
  "stuff": 2626,
  "difficulty": 2627,
  "grandson.": 2628,
  "mentioned,": 2629,
  "youngsters": 2630,
  "into.": 2631,
  "fancy,": 2632,
  "gold.": 2633,
  "remain": 2634,
  "necessary,": 2635,
  "baffled": 2636,
  "awful.": 2637,
  "customer": 2638,
  "meet.": 2639,
  "lightweight,": 2640,
  "keeps": 2641,
  "hurt": 2642,
  "arm.": 2643,
  "price?.": 2644,
  "Look": 2645,
  "Ho": 2646,
  "https://drop.ndtv.com/TECH/product_database/images/712016104329AM_635_vivo_x7_plus.jpeg?downsize=*:180&output-quality=80&output-format=webp": 2647,
  "serious?": 2648,
  "feeling?": 2649,
  "true?": 2650,
  "L12.": 2651,
  "does,": 2652,
  "grandson": 2653,
  "instead": 2654,
  "hime": 2655,
  "hurry,": 2656,
  "Nokia.": 2657,
  "Two": 2658,
  "power.": 2659,
  "silver.": 2660,
  "Nikon.": 2661,
  "good.Show": 2662,
  "Anything.": 2663,
  "spare.": 2664,
  "No?": 2665,
  "lucky": 2666,
  "Premium,": 2667,
  "thoroughly": 2668,
  "helped.": 2669,
  "GPS.": 2670,
  "Absolutely.": 2671,
  "myself?": 2672,
  "feedback": 2673,
  "specify": 2674,
  "back,": 2675,
  "watched": 2676,
  "commercial": 2677,
  "newspaper.": 2678,
  "remember,": 2679,
  "evo?": 2680,
  "amust": 2681,
  "longer,": 2682,
  "top-notch": 2683,
  "offering?": 2684,
  "primarily": 2685,
  "studies.": 2686,
  "IPads.": 2687,
  "rate": 2688,
  "iPhone?": 2689,
  "IPad": 2690,
  "https://drop.ndtv.com/TECH/product_database/images/910201514439AM_635_apple_ipad_mini_4_wi_fi.jpeg?downsize=*:180&output-quality=80&output-format=webp": 2691,
  "Dell,": 2692,
  "relevant": 2693,
  "https://encrypted-tbn0.gstatic.com/images?q=tbn:ANd9GcQDVRP8jdLxq1ftCOpSmzlBbJVUZEBRbbFnjw&usqp=CAU": 2694,
  "coding.": 2695,
  "2000:3000": 2696,
  "classes.": 2697,
  "inch,": 2698,
  "2700mAh": 2699,
  "only!": 2700,
  "disappointing.": 2701,
  "entire": 2702,
  "Therefore,": 2703,
  "colour!": 2704,
  "Hmm,": 2705,
  "43254785": 2706,
  "critical": 2707,
  "Billing?": 2708,
  "photos.": 2709,
  "selection.": 2710,
  "afternoon.Can": 2711,
  "No:": 2712,
  "ZE553KL.": 2713,
  "https://fdn2.gsmarena.com/vv/bigpic/acer-iconia-talk-s.jpg": 2714,
  "Hiii,": 2715,
  "smartphone.Can": 2716,
  "packed": 2717,
  "3!": 2718,
  "graphics_card?": 2719,
  "family": 2720,
  "deplorable.": 2721,
  "2000-4000": 2722,
  "OK,!": 2723,
  "Support": 2724,
  "external": 2725,
  "MIC?": 2726,
  "Will,": 2727,
  "CL45,": 2728,
  "Clik!?": 2729,
  "either.": 2730,
  "alink:": 2731,
  "Aspire": 2732,
  "A515-54G": 2733,
  "Volta": 2734,
  "picture-": 2735,
  "https://tse2.mm.bing.net/th?id=OIP.1pNnvVMHqBsg8FDsAjlHAQHaEx&pid=Api&P=0&w=267&h=173": 2736,
  "https://tse2.mm.bing.net/th?id=OIP.pECCv2VVGJWU_E4PbRovxAHaFj&pid=Api&P=0&w=201&h=152": 2737,
  "including": 2738,
  "DELL": 2739,
  "uses?": 2740,
  "differences": 2741,
  "vast": 2742,
  "Xiaomi.": 2743,
  "ram,": 2744,
  "https://www.samsung.com/global/galaxy/galaxys6/galaxy-s6-edge/images/galaxy-s6-edge_feature_next-gen-processor.jpg": 2745,
  "FinePix": 2746,
  "F810": 2747,
  "XOLO.": 2748,
  "150-200": 2749,
  "they?": 2750,
  "2500mAh": 2751,
  "Q1000s.": 2752,
  "Yesbookit.": 2753,
  "https://tse2.mm.bing.net/th?id=OIP.pECCv2VVGJWU_E4PbRovxAHaFj&pid=Api&P=0&w=201&h=152.": 2754,
  "https://tse2.mm.bing.net/th?id=OIP._cVNcHCSWwbFCtERyYJUjAAAAA&pid=Api&P=0&w=300&h=300.": 2755,
  "intelligent": 2756,
  "neighbour.": 2757,
  "sending": 2758,
  "cause": 2759,
  "https://drop.ndtv.com/TECH/product_database/images/lenovo_vibe_p1_database_ndtv_2925_480X960_1229201564818PM.jpg?downsize=*:180&output-quality=80&output-format=webp": 2760,
  "Size": 2761,
  "dancing.": 2762,
  "https://drop.ndtv.com/TECH/product_database/images/531201621827PM_635_lenovo_zuk_2_black.jpeg?downsize=*:180&output-quality=80&output-format=webp": 2763,
  "ZUK": 2764,
  "Z2.": 2765,
  "photoshoot": 2766,
  "project.": 2767,
  "DMC-LC40": 2768,
  "weights?": 2769,
  "S4": 2770,
  "https://drop.ndtv.com/TECH/product_database/images/11172016111139AM_635_vivo_xplay6.jpeg?downsize=*:180&output-quality=80&output-format=webp\ndo": 2771,
  "https://drop.ndtv.com/TECH/product_database/images/xiaomi_mi5_db_ndtv_3344_480X960_47201634632PM.jpg?downsize=*:80&output-quality=70": 2772,
  "Mini.": 2773,
  "son,": 2774,
  "Still": 2775,
  "technical": 2776,
  "fade": 2777,
  "zoomed": 2778,
  "in.": 2779,
  "entirely": 2780,
  "cheaper?": 2781,
  "handheld": 2782,
  "travel,": 2783,
  "http://latestcamera.com/wp\u0002content/uploads/2016/03/WP_20160305_08_09_48_Pro.jpg": 2784,
  "big.": 2785,
  "OK": 2786,
  "Nothing": 2787,
  "nice,": 2788,
  "35k": 2789,
  "domain?": 2790,
  "9'": 2791,
  "small-sized": 2792,
  "local": 2793,
  "https://drop.ndtv.com/TECH/product_database/images/gionee_a1_black_4044_480X960_472017111011AM.jpg?downsize=*:180&output-quality=80&output-format=webp": 2794,
  "https://images-na.ssl-images-amazon.com/images/I/71ZA7q5NzfL._AC_SL1500_.jpg": 2795,
  "NO-NO.": 2796,
  "Sapphire": 2797,
  "bill.": 2798,
  "Google?": 2799,
  "Pixel": 2800,
  "Xl.": 2801,
  "Battery?": 2802,
  "15i": 2803,
  "nch": 2804,
  "Compact": 2805,
  "clicks": 2806,
  "underwater": 2807,
  "meant.": 2808,
  "CPU": 2809,
  "Precisely": 2810,
  "sort": 2811,
  "Choosing": 2812,
  "tricky.": 2813,
  "sequence": 2814,
  "aiming": 2815,
  "worthy.": 2816,
  "extended": 2817,
  "resolutions": 2818,
  "EX-V8.": 2819,
  "prices,": 2820,
  "debut?": 2821,
  "advance.": 2822,
  "happen": 2823,
  "2000,": 2824,
  "born.": 2825,
  "Kodak": 2826,
  "manufactured": 2827,
  "rates?": 2828,
  "higher.": 2829,
  "towards": 2830,
  "precise": 2831,
  "option,": 2832,
  "undoubtedly": 2833,
  "notebook": 2834,
  "easily.": 2835,
  "be?": 2836,
  "scale": 2837,
  "edition": 2838,
  "forms": 2839,
  "touchscreen.": 2840,
  "15.6-": 2841,
  "reduced": 2842,
  "Morning!!": 2843,
  "retro": 2844,
  "900S": 2845,
  "OnePlus.": 2846,
  "offering": 2847,
  "OnePlus": 2848,
  "450": 2849,
  "variants.": 2850,
  "giving": 2851,
  "F9s.": 2852,
  "don't.": 2853,
  "800": 2854,
  "https://drop.ndtv.com/TECH/product_database/images/1122016124559PM_635_alcatel_idol_4s_windows.jpeg?downsize=*:180&output-quality=80&output-format=webp": 2855,
  "double": 2856,
  "favour?": 2857,
  "career": 2858,
  "Using": 2859,
  "3GBRAM": 2860,
  "5mp": 2861,
  "front": 2862,
  "13mp": 2863,
  "rear": 2864,
  "megapixels?": 2865,
  "Evening!": 2866,
  "Laptop": 2867,
  "Laptop.": 2868,
  "i7-8550U.": 2869,
  "perfectly": 2870,
  "tablet.could": 2871,
  "18th": 2872,
  "longing": 2873,
  "https://fdn2.gsmarena.com/vv/bigpic/toshiba-excite-13-AT335.jpg": 2874,
  "confusing": 2875,
  "EX-V8": 2876,
  "trending": 2877,
  "nowadays.": 2878,
  "500-700": 2879,
  "born": 2880,
  "Kodak.": 2881,
  "What're": 2882,
  "2028.": 2883,
  "5999": 2884,
  "alternative": 2885,
  "Fujifilm.": 2886,
  "lately?": 2887,
  "anywhere.": 2888,
  "Above": 2889,
  "spaces?": 2890,
  "version": 2891,
  "types?": 2892,
  "recommendations": 2893,
  "tag": 2894,
  "previously.": 2895,
  "life.": 2896,
  "4G.": 2897,
  "skipped": 2898,
  "two?": 2899,
  "sizes,": 2900,
  "block": 2901,
  "may,": 2902,
  "attention": 2903,
  "three": 2904,
  "agree.": 2905,
  "HTC's": 2906,
  "recent?": 2907,
  "greater": 2908,
  "5000mAh.": 2909,
  "adequate.": 2910,
  "borrow": 2911,
  "while?": 2912,
  "hoped.": 2913,
  "proposed": 2914,
  "reading.": 2915,
  "hand?": 2916,
  "include": 2917,
  "Amazon": 2918,
  "Books": 2919,
  "subscription?": 2920,
  "LTE": 2921,
  "connection?": 2922,
  "each": 2923,
  "wonderful": 2924,
  "reasons.": 2925,
  "support": 2926,
  "dark.": 2927,
  "output": 2928,
  "realm": 2929,
  "capturing": 2930,
  "memories.": 2931,
  "appealing,": 2932,
  "Samsung-exclusive": 2933,
  "charcoal": 2934,
  "original?": 2935,
  "town": 2936,
  "considered.": 2937,
  "convinced,": 2938,
  "substance": 2939,
  "decisions.": 2940,
  "intriguing!!": 2941,
  "ones.": 2942,
  "monitor,": 2943,
  "nearly": 2944,
  "wide.": 2945,
  "sorry!!": 2946,
  "favourites!!": 2947,
  "line": 2948,
  "apologise": 2949,
  "forgetting": 2950,
  "inquire": 2951,
  "window": 2952,
  "lucrative": 2953,
  "reliable?\nWill": 2954,
  "massive": 2955,
  "highlights?": 2956,
  "high-definition": 2957,
  "invoice": 2958,
  "recommending": 2959,
  "model.\nhttps://fdn2.gsmarena.com/vv/bigpic/allview-x4s.jpg\nis": 2960,
  "background": 2961,
  "hear,": 2962,
  "individual.": 2963,
  "complete": 2964,
  "process": 2965,
  "safest.": 2966,
  "improved": 2967,
  "battery's": 2968,
  "takes": 2969,
  "HD": 2970,
  "regard": 2971,
  "https://static.toiimg.com/thumb/resizemode-4,msid-54171358,width-160/54171358.jpg\nfor": 2972,
  "qualities.": 2973,
  "high,": 2974,
  "endorse": 2975,
  "cards?": 2976,
  "wrap": 2977,
  "popular": 2978,
  "showing.": 2979,
  "appropriate.": 2980,
  "desires": 2981,
  "desktop.": 2982,
  "location": 2983,
  "heck!": 2984,
  "exorbitant?": 2985,
  "one's": 2986,
  "dad.": 2987,
  "fitness": 2988,
  "classes": 2989,
  "internet.": 2990,
  "accommodate": 2991,
  "powered": 2992,
  "being.": 2993,
  "day,": 2994,
  "produces": 2995,
  "spectrum": 2996,
  "charger.": 2997,
  "lens's": 2998,
  "focal": 2999,
  "unimportant.": 3000,
  "grading?": 3001,
  "room.": 3002,
  "commodity": 3003,
  "anywhere": 3004,
  "dollars.": 3005,
  "designed": 3006,
  "room,": 3007,
  "518-pixel": 3008,
  "products?": 3009,
  "aluminium.": 3010,
  "dance": 3011,
  "allow": 3012,
  "downside,": 3013,
  "Motorola.": 3014,
  "abandon": 3015,
  "plan.": 3016,
  "key": 3017,
  "scan": 3018,
  "she'll": 3019,
  "adore.": 3020,
  "nephew,": 3021,
  "precedence.128": 3022,
  "qualities": 3023,
  "screenshots?": 3024,
  "x": 3025,
  "768": 3026,
  "awesome,": 3027,
  "consistency": 3028,
  "weigh,": 3029,
  "comparable-priced": 3030,
  "We'd": 3031,
  "tutor.": 3032,
  "ones?": 3033,
  "silver,": 3034,
  "ma": 3035,
  "boloking.": 3036,
  "developer": 3037,
  "engineering.": 3038,
  "GPU": 3039,
  "compact": 3040,
  "optical": 3041,
  "viewfinder": 3042,
  "used.": 3043,
  "published": 3044,
  "2015.": 3045,
  "newly": 3046,
  "lighter": 3047,
  "weight.": 3048,
  "GPS-enabled": 3049,
  "dual-sim?": 3050,
  "resembles": 3051,
  "collection?": 3052,
  "desired": 3053,
  "friend's": 3054,
  "filmmaker.": 3055,
  "list?": 3056,
  "extent": 3057,
  "picky": 3058,
  "model?\nIs": 3059,
  "mentioned?": 3060,
  "lesson.": 3061,
  "qualify": 3062,
  "installed": 3063,
  "brands?": 3064,
  "3.75": 3065,
  "double-check": 3066,
  "mother": 3067,
  "gifting": 3068,
  "unsure": 3069,
  "DMC-L1,": 3070,
  "2006.": 3071,
  "EX-Z77": 3072,
  "box": 3073,
  "owned": 3074,
  "opinion": 3075,
  "spend,": 3076,
  "consistency.": 3077,
  "distinct": 3078,
  "visuals?": 3079,
  "Simply": 3080,
  "reliable.": 3081,
  "Elite.": 3082,
  "specifics,": 3083,
  "https://tse3.mm.bing.net/th?id=OIP.OPzZiQtdFWw7YckTOD-0DgHaGr&pid=Api&P=0&w=172&h=156&pid=Api&P=0&w=172&h=156": 3084,
  "capabilities.": 3085,
  "inside.": 3086,
  "concluded": 3087,
  "versatile": 3088,
  "publish": 3089,
  "responsible": 3090,
  "argument.": 3091,
  "ought": 3092,
  "reconsider.": 3093,
  "Active": 3094,
  "peers": 3095,
  "boasting": 3096,
  "operate.": 3097,
  "arrives.": 3098,
  "cool,": 3099,
  "predict.": 3100,
  "selective": 3101,
  "mindful": 3102,
  "qualities,": 3103,
  "expected.complete": 3104,
  "phrase,": 3105,
  "clause": 3106,
  "money!": 3107,
  "stick": 3108,
  "concern,": 3109,
  "Lenovo's": 3110,
  "330S,": 3111,
  "depressing!": 3112,
  "explanation": 3113,
  "SSDs": 3114,
  "quicker.": 3115,
  "inquired,": 3116,
  "loss": 3117,
  "words.": 3118,
  "wondering.": 3119,
  "one-of-a-kind": 3120,
  "usual.": 3121,
  "attractive.": 3122,
  "costly,": 3123,
  "L1": 3124,
  "colleagues.": 3125,
  "hand.": 3126,
  "continue.": 3127,
  "distinctive": 3128,
  "identical": 3129,
  "Students": 3130,
  "taught": 3131,
  "applications": 3132,
  "pupils.": 3133,
  "break?": 3134,
  "adore": 3135,
  "beginner,": 3136,
  "needed": 3137,
  "inexpensive.": 3138,
  "shows": 3139,
  "cam": 3140,
  "Price.": 3141,
  "GJ": 3142,
  "E975.": 3143,
  "950XL": 3144,
  "means": 3145,
  "windows?": 3146,
  "booked": 3147,
  "named": 3148,
  "impressed": 3149,
  "Zenfones": 3150,
  "shining": 3151,
  "brightly.": 3152,
  "concentrate": 3153,
  "physical": 3154,
  "approximatelt": 3155,
  "yesterday.": 3156,
  "closest": 3157,
  "wide?": 3158,
  "trendy": 3159,
  "purpose.": 3160,
  "D60": 3161,
  "haven't": 3162,
  "dimensions?": 3163,
  "tha": 3164,
  "80-100": 3165,
  "oldest": 3166,
  "P1.": 3167,
  "vintage": 3168,
  "each?": 3169,
  "D-300l": 3170,
  "4100.": 3171,
  "4100": 3172,
  "799": 3173,
  "Toshiba.": 3174,
  "700euros": 3175,
  "concerned.\nFor": 3176,
  "feature,": 3177,
  "Ant": 3178,
  "aspects.": 3179,
  "Macbook.": 3180,
  "18.4": 3181,
  "sizes.": 3182,
  "Note.": 3183,
  "mor": 3184,
  "https://gsmorigin.com/wp-content/uploads/2018/04/Lava-Z25.jpg": 3185,
  "Definitely": 3186,
  "smatphone": 3187,
  "lasting": 3188,
  "Sonim.": 3189,
  "poor": 3190,
  "wins": 3191,
  "6.": 3192,
  "youtube": 3193,
  "vlogger": 3194,
  "2GB": 3195,
  "difficult": 3196,
  "doesnot": 3197,
  "3500mAh": 3198,
  "adjust": 3199,
  "years.": 3200,
  "700EUR.": 3201,
  "Aurora.": 3202,
  "intresting.": 3203,
  "6GB": 3204,
  "smoothly.": 3205,
  "gamers.": 3206,
  "M6s": 3207,
  "Plus?": 3208,
  "surely": 3209,
  "100EUR.": 3210,
  "Mega?": 3211,
  "hearing": 3212,
  "sizes": 3213,
  "14inch": 3214,
  "Afternoon.": 3215,
  "Hoe": 3216,
  "small": 3217,
  "microphone": 3218,
  "CL45": 3219,
  "Clik?": 3220,
  "gap": 3221,
  "instead.": 3222,
  "since": 3223,
  "efficiency": 3224,
  "gap.": 3225,
  "transmitter": 3226,
  "memory.": 3227,
  "components": 3228,
  "limited.": 3229,
  "brands,": 3230,
  "decrease.": 3231,
  "An": 3232,
  "specifics.": 3233,
  "trust.": 3234,
  "be.\nhttps://rukminim1.flixcart.com/image/416/416/je09ua80/mobile/e/s/j/gionee-s6-pro-s6-pro-original-imaf2shkbxgpvdmh.jpeg?q=70": 3235,
  "photographs.": 3236,
  "broad": 3237,
  "spectrum.": 3238,
  "fare": 3239,
  "sims.": 3240,
  "scoring": 3241,
  "referring": 3242,
  "Create": 3243,
  "monitor.": 3244,
  "consideration,": 3245,
  "wisest": 3246,
  "platform": 3247,
  "things.\nI": 3248,
  "upload": 3249,
  "items,": 3250,
  "blame": 3251,
  "reconsider": 3252,
  "position.": 3253,
  "it.Thank": 3254,
  "purchasing.": 3255,
  "distinct.": 3256,
  "resource": 3257,
  "absolutely.": 3258,
  "wasn't": 3259,
  "expecting.": 3260,
  "Except": 3261,
  "took": 3262,
  "appearance": 3263,
  "prefers.": 3264,
  "without": 3265,
  "striking": 3266,
  "concerned": 3267,
  "completely": 3268,
  "enamoured": 3269,
  "son's": 3270,
  "fifteen": 3271,
  "call.": 3272,
  "suppose.": 3273,
  "laptops,": 3274,
  "13-megapixel": 3275,
  "8-megapixel": 3276,
  "you'll": 3277,
  "manufacturer.": 3278,
  "feels.": 3279,
  "rose": 3280,
  "attractive?": 3281,
  "hard.": 3282,
  "fantasy": 3283,
  "account.": 3284,
  "hands": 3285,
  "descriptive.": 3286,
  "kinds.\nAs": 3287,
  "HP,": 3288,
  "depending": 3289,
  "drive": 3290,
  "results,": 3291,
  "mean?": 3292,
  "Vivo's.": 3293,
  "Cameras": 3294,
  "aren't": 3295,
  "advanced": 3296,
  "computer.": 3297,
  "doubts.": 3298,
  "justified": 3299,
  "aspiring": 3300,
  "Mobile.": 3301,
  "think?": 3302,
  "capabilities?": 3303,
  "expenditure": 3304,
  "cap.": 3305,
  "pursuing": 3306,
  "degree": 3307,
  "journalism.": 3308,
  "studying": 3309,
  "tools,": 3310,
  "results.": 3311,
  "shape.": 3312,
  "reassurance.": 3313,
  "notebook.": 3314,
  "smartphones,": 3315,
  "fallen": 3316,
  "commodity.": 3317,
  "feminine": 3318,
  "approaching.": 3319,
  "pricey;": 3320,
  "Whatever": 3321,
  "deciding,": 3322,
  "informed.": 3323,
  "together": 3324,
  "say?": 3325,
  "true": 3326,
  "probably": 3327,
  "Force": 3328,
  "informed": 3329,
  "euros.Could": 3330,
  "skilled": 3331,
  "truly": 3332,
  "considering.": 3333,
  "dilemma.": 3334,
  "technological": 3335,
  "items": 3336,
  "join": 3337,
  "guy": 3338,
  "insisted": 3339,
  "particular.": 3340,
  "par?": 3341,
  "labels,": 3342,
  "somebody.": 3343,
  "model's": 3344,
  "appears.": 3345,
  "beneficial?": 3346,
  "https://i.ytimg.com/vi/Pu5U7JGZXsY/hqdefault.jpg": 3347,
  "light.": 3348,
  "reduce": 3349,
  "A10": 3350,
  "started.": 3351,
  "that'll": 3352,
  "magnification": 3353,
  "appropriate": 3354,
  "worthwhile": 3355,
  "cameras,": 3356,
  "trouble": 3357,
  "analysis": 3358,
  "grandchildren.": 3359,
  "begun": 3360,
  "believe,": 3361,
  "requirement:": 3362,
  "Young": 3363,
  "people": 3364,
  "nowadays": 3365,
  "appearance.": 3366,
  "standard?": 3367,
  "what's": 3368,
  "sporting?": 3369,
  "lovely.": 3370,
  "end-of-season": 3371,
  "auction.": 3372,
  "Phones": 3373,
  "recommendations,": 3374,
  "suspect.": 3375,
  "increased": 3376,
  "maintained": 3377,
  "level.": 3378,
  "appropriate,": 3379,
  "Right": 3380,
  "convenience.": 3381,
  "debacle.": 3382,
  "grateful": 3383,
  "receives": 3384,
  "client.": 3385,
  "Cousin": 3386,
  "holds": 3387,
  "His": 3388,
  "arm": 3389,
  "affected": 3390,
  "Limit": 3391,
  "down.": 3392,
  "scale.": 3393,
  "sufficient.": 3394,
  "Find": 3395,
  "coupon": 3396,
  "Cannon": 3397,
  "wise": 3398,
  "set,": 3399,
  "example?": 3400,
  "person's": 3401,
  "\"How": 3402,
  "cost?\"": 3403,
  "\"I": 3404,
  "intended": 3405,
  "had.": 3406,
  "reservations": 3407,
  "tense.": 3408,
  "case,\nhttps://drop.ndtv.com/TECH/product_database/images/712016104329AM_635_vivo_x7_plus.jpeg?downsize=*:180&output-quality=80&output-format=webp": 3409,
  "kidding?": 3410,
  "To": 3411,
  "They,": 3412,
  "precise.": 3413,
  "convinced.": 3414,
  "inclined": 3415,
  "cash.": 3416,
  "tried": 3417,
  "lacks": 3418,
  "feel?": 3419,
  "size,": 3420,
  "device.": 3421,
  "choices": 3422,
  "L12,": 3423,
  "explain.": 3424,
  "safer": 3425,
  "rush,": 3426,
  "They're": 3427,
  "Gold,": 3428,
  "hand,": 3429,
  "uneasy.": 3430,
  "clear": 3431,
  "example.": 3432,
  "vicinity": 3433,
  "EUR.However,": 3434,
  "convenient": 3435,
  "users": 3436,
  "stolen,": 3437,
  "train": 3438,
  "catch.": 3439,
  "late.": 3440,
  "haste.": 3441,
  "required": 3442,
  "fortunate": 3443,
  "refers": 3444,
  "visible": 3445,
  "Premium?": 3446,
  "beneficial.": 3447,
  "fully": 3448,
  "knowledgeable.": 3449,
  "pricey?": 3450,
  "purple.": 3451,
  "Excellent": 3452,
  "functionality.": 3453,
  "morning": 3454,
  "hello.": 3455,
  "2017.": 3456,
  "compatible": 3457,
  "\"o,": 3458,
  "reviews": 3459,
  "advertisement": 3460,
  "newspaper": 3461,
  "ago.": 3462,
  "recall,": 3463,
  "U": 3464,
  "Ultra?": 3465,
  "evo's": 3466,
  "selling": 3467,
  "silver?": 3468,
  "investigate": 3469,
  "indefinitely": 3470,
  "safest": 3471,
  "insufficient.": 3472,
  "mainly": 3473,
  "education": 3474,
  "iPads": 3475,
  "certain.": 3476,
  "Apple's": 3477,
  "performing?": 3478,
  "you'd": 3479,
  "iPhone": 3480,
  "knowledgeable": 3481,
  "fill": 3482,
  "thoughts": 3483,
  "iPhone's": 3484,
  "good?\nhttps://fdn2.gsmarena.com/vv/bigpic/ipad-mini-41.jpg": 3485,
  "https://fdn2.gsmarena.com/vv/bigpic/acer-iconia-smart-new.jpg": 3486,
  "coding": 3487,
  "despise.": 3488,
  "buddy,": 3489,
  "courses,": 3490,
  "favours": 3491,
  "charcoal.": 3492,
  "2700mAh!": 3493,
  "disappointment.": 3494,
  "preferable.": 3495,
  "whole": 3496,
  "enormous": 3497,
  "black!": 3498,
  "he'll": 3499
}